axians_mcp/__init__.py
axians_mcp/servers/__init__.py
axians_mcp/servers/iceland.py
axians_mcp/servers/main.py
axians_mcp/servers/utils.py
axians_mcp/servers/weather.py
axians_mcp-1.2.2.dist-info/METADATA
axians_mcp-1.2.2.dist-info/WHEEL
axians_mcp-1.2.2.dist-info/entry_points.txt
axians_mcp-1.2.2.dist-info/RECORD
